cgt/__init__.py
cgt/constants.py
cgt/distances.py
cgt/enums.py
cgt/examples.py
cgt/genome.py
cgt/hyperoctahedral.py
cgt/models.py
cgt/parsers.py
cgt/pickle_manager.py
cgt/plotting.py
cgt/position_paradigm.py
cgt/rearrangements.py
cgt/simulations.py
cgt/sorting.py
cgt/structures.py
cgt/visualisation.py
cgt/tests/__init__.py
cgt/tests/test_conversions.py
cgt/tests/test_hyperoctahedral.py
cgt/tests/test_min_distances.py
cgt-0.4.3.dist-info/LICENSE
cgt-0.4.3.dist-info/METADATA
cgt-0.4.3.dist-info/WHEEL
cgt-0.4.3.dist-info/top_level.txt
cgt-0.4.3.dist-info/RECORD
