Metadata-Version: 2.1
Name: cgt
Version: 0.4.3
Summary: Tools for representing genomes in sage
Home-page: https://github.com/js51/Circular-genome-tools
Author: Joshua Stevenson
Author-email: joshua.stevenson@utas.edu.au
Classifier: Programming Language :: Python :: 3
Classifier: License :: OSI Approved :: MIT License
Classifier: Operating System :: OS Independent
Requires-Python: >=3
License-File: LICENSE
